{"mask_name": "mask_000001.npy", "mask_height": 900, "mask_width": 1600, "promote_type": "mask", "labels": {"1": {"instance_id": 1, "class_name": "car", "x1": 808, "y1": 495, "x2": 846, "y2": 529, "logit": 0.0}, "2": {"instance_id": 2, "class_name": "car", "x1": 498, "y1": 442, "x2": 782, "y2": 727, "logit": 0.0}, "3": {"instance_id": 3, "class_name": "car", "x1": 762, "y1": 493, "x2": 797, "y2": 539, "logit": 0.0}, "4": {"instance_id": 4, "class_name": "car", "x1": 768, "y1": 492, "x2": 800, "y2": 519, "logit": 0.0}}}