{"mask_name": "mask_000031.npy", "mask_height": 900, "mask_width": 1600, "promote_type": "mask", "labels": {"22": {"instance_id": 22, "class_name": "car", "x1": 1305, "y1": 484, "x2": 1599, "y2": 675, "logit": 0.0}, "8": {"instance_id": 8, "class_name": "car", "x1": 863, "y1": 480, "x2": 926, "y2": 531, "logit": 0.0}, "25": {"instance_id": 25, "class_name": "car", "x1": 1304, "y1": 484, "x2": 1599, "y2": 675, "logit": 0.0}, "26": {"instance_id": 26, "class_name": "bus", "x1": 343, "y1": 447, "x2": 522, "y2": 592, "logit": 0.0}, "27": {"instance_id": 27, "class_name": "laneline", "x1": 361, "y1": 522, "x2": 805, "y2": 884, "logit": 0.0}}}